whois/__init__.py
whois/parser.py
whois/time_zones.py
whois/whois.py
whois/data/public_suffix_list.dat
python_whois-0.9.3.dist-info/LICENSE.txt
python_whois-0.9.3.dist-info/METADATA
python_whois-0.9.3.dist-info/WHEEL
python_whois-0.9.3.dist-info/top_level.txt
python_whois-0.9.3.dist-info/RECORD
