Metadata-Version: 2.1
Name: python-whois
Version: 0.9.3
Summary: Whois querying and parsing of domain registration information.
Home-page: https://github.com/richardpenman/whois
Author: Richard Penman
Author-email: richard.penman@gmail.com
License: MIT
Keywords: whois,python
Classifier: Environment :: Web Environment
Classifier: Intended Audience :: Developers
Classifier: License :: OSI Approved :: MIT License
Classifier: Operating System :: OS Independent
Classifier: Programming Language :: Python
Classifier: Topic :: Internet :: WWW/HTTP
Classifier: Programming Language :: Python :: 3
License-File: LICENSE.txt
